{
  "coinzy": {
    "privacy": {
      "title": "Coinzy – Privacy Policy",
      "markdownFile": "coinzy/privacy.md",
      "analyticsPage": "coinzy-privacy"
    },
    "terms": {
      "title": "Coinzy: Terms of Service",
      "markdownFile": "coinzy/terms.md",
      "analyticsPage": "coinzy-terms"
    }
  },
  "banknotes": {
    "privacy": {
      "title": "Banknote Identification AI: Privacy Policy",
      "markdownFile": "banknotes/privacy.md",
      "analyticsPage": "banknote-privacy"
    },
    "terms": {
      "title": "Banknote Identification AI: Terms of Service",
      "markdownFile": "banknotes/terms.md",
      "analyticsPage": "banknote-terms"
    }
  },
  "insecto": {
    "privacy": {
      "title": "Insecto AI: Bug Identifier — Privacy Policy",
      "markdownFile": "insecto/privacy.md",
      "analyticsPage": "insecto-privacy"
    },
    "terms": {
      "title": "Insecto AI: Bug Identifier — Terms and Conditions",
      "markdownFile": "insecto/terms.md",
      "analyticsPage": "insecto-terms"
    }
  },
  "habiteazy": {
    "privacy": {
      "title": "Habit Eazy: Privacy Policy",
      "markdownFile": "habiteazy/privacy.md",
      "analyticsPage": "habiteazy-privacy"
    },
    "terms": {
      "title": "Habit Eazy: Terms and Conditions",
      "markdownFile": "habiteazy/terms.md",
      "analyticsPage": "habiteazy-terms"
    }
  },
  "rockzy": {
    "privacy": {
      "title": "Rockzy: AI Rock Identifier – Privacy Policy",
      "markdownFile": "rockzy/privacy.md",
      "analyticsPage": "rockzy-privacy"
    },
    "terms": {
      "title": "Rockzy: AI Rock Identifier — Terms of Service",
      "markdownFile": "rockzy/terms.md",
      "analyticsPage": "rockzy-terms"
    }
  }
}
